<?xml version="1.0" encoding="UTF-8" standalone="yes"?>
<scenario id="1">
    <name>a</name>
    <numberConsumerProvider>1</numberConsumerProvider>
    <consumers>
        <consumers>
            <id>1</id>
            <requestBySeconde>1</requestBySeconde>
        </consumers>
    </consumers>
    <providers>
        <providers>
            <id>1</id>
            <dataExchangeSize typeBehavior="ms">
                <content>1</content>
            </dataExchangeSize>
            <processingTime timeUnit="ms">
                <content>2</content>
            </processingTime>
        </providers>
    </providers>
</scenario>
